flask_mqtt/__init__.py
Flask_MQTT-1.2.1.dist-info/LICENSE
Flask_MQTT-1.2.1.dist-info/METADATA
Flask_MQTT-1.2.1.dist-info/WHEEL
Flask_MQTT-1.2.1.dist-info/top_level.txt
Flask_MQTT-1.2.1.dist-info/RECORD
