Metadata-Version: 2.1
Name: Flask-MQTT
Version: 1.2.1
Summary: Flask extension for the MQTT protocol
Home-page: https://github.com/MrLeeh/Flask-MQTT
Author: Stefan Lehmann
Author-email: stefan.st.lehmann@gmail.com
License: MIT
Platform: any
Classifier: Development Status :: 5 - Production/Stable
Classifier: Environment :: Web Environment
Classifier: Intended Audience :: Developers
Classifier: License :: OSI Approved :: MIT License
Classifier: Programming Language :: Python
Classifier: Topic :: Internet :: WWW/HTTP :: Dynamic Content
Classifier: Topic :: Software Development :: Libraries :: Python Modules
Requires-Python: >=3.6
License-File: LICENSE
Requires-Dist: Flask
Requires-Dist: paho-mqtt<2.0
